pump/__init__.py
pump/downloader.py
pump/utils.py
pump_downloader-0.2.2.dist-info/LICENSE
pump_downloader-0.2.2.dist-info/METADATA
pump_downloader-0.2.2.dist-info/WHEEL
pump_downloader-0.2.2.dist-info/entry_points.txt
pump_downloader-0.2.2.dist-info/top_level.txt
pump_downloader-0.2.2.dist-info/RECORD
