Metadata-Version: 2.1
Name: pump-downloader
Version: 0.2.2
Summary: Multithreaded downloader for faster downloads
Home-page: https://github.com/thevarunsharma/pump-downloader
Author: Varun Sharma
Keywords: download pump curl wget concurrent parallel
Classifier: Programming Language :: Python :: 3
Classifier: License :: OSI Approved :: Apache Software License
Classifier: Operating System :: OS Independent
Requires-Python: >=3.8
License-File: LICENSE
Requires-Dist: Click
Requires-Dist: requests
Requires-Dist: tqdm
